quote_arg_for_cmd.py
quote_arg_for_cmd-0.1.0.dist-info/licenses/LICENSE
quote_arg_for_cmd-0.1.0.dist-info/METADATA
quote_arg_for_cmd-0.1.0.dist-info/WHEEL
quote_arg_for_cmd-0.1.0.dist-info/top_level.txt
quote_arg_for_cmd-0.1.0.dist-info/RECORD
