Metadata-Version: 2.4
Name: quote-arg-for-cmd
Version: 0.1.0
Summary: Safely quotes Python 2 and 3 `str`s for use as command-line arguments passed to `cmd.exe`. Read `README.md` for caveats.
Author-email: Jifeng Wu <jifengwu2k@gmail.com>
License-Expression: MIT
Project-URL: Homepage, https://github.com/jifengwu2k/quote-arg-for-cmd
Project-URL: Bug Tracker, https://github.com/jifengwu2k/quote-arg-for-cmd/issues
Classifier: Programming Language :: Python :: 2
Classifier: Programming Language :: Python :: 3
Requires-Python: >=2
License-File: LICENSE
Dynamic: license-file
